{
  "_id": "hxhIMzbdK5CHnAga",
  "name": "Banish to Faerie",
  "type": "feat",
  "img": "modules/pf1spheres/assets/icons/spheres/fallen_fey.webp",
  "effects": [],
  "folder": null,
  "sort": 0,
  "flags": {
    "pf1spheres": {
      "sphere": "fallenFey"
    }
  },
  "system": {
    "description": {
      "value": "<p><strong>Prerequisites:</strong> 8th caster or higher.</p>\n<p>As a standard action, you may spend a spell point to make a melee touch attack against a creature and hurl it into Faerie. This provokes an attack of opportunity. A successful Will save negates this ability. Once within Faerie, if the target creature wishes to return to where it previously was, it must travel 1d12 miles to reach a fairy circle and find a way through, arriving within 1d6 miles of its former location. This is a teleportation effect.</p>\n",
      "chat": "",
      "unidentified": ""
    },
    "tags": [],
    "actions": [],
    "uses": {
      "per": null,
      "value": 0,
      "maxFormula": "",
      "autoDeductCharges": true,
      "autoDeductChargesCost": "1"
    },
    "attackNotes": [],
    "effectNotes": [],
    "changes": [],
    "changeFlags": {
      "loseDexToAC": false,
      "noEncumbrance": false,
      "mediumArmorFullSpeed": false,
      "heavyArmorFullSpeed": false
    },
    "contextNotes": [],
    "links": {
      "children": [],
      "charges": []
    },
    "tag": "",
    "useCustomTag": false,
    "armorProf": {
      "value": [],
      "custom": ""
    },
    "weaponProf": {
      "value": [],
      "custom": ""
    },
    "languages": {
      "value": [],
      "custom": ""
    },
    "flags": {
      "boolean": {},
      "dictionary": {}
    },
    "scriptCalls": [],
    "featType": "magicTalent",
    "associations": {
      "classes": []
    },
    "showInQuickbar": false,
    "abilityType": "none",
    "crOffset": "",
    "disabled": false,
    "classSkills": {},
    "nonlethal": false,
    "activation": {
      "cost": 1,
      "type": ""
    },
    "unchainedAction": {
      "activation": {
        "cost": 1,
        "type": ""
      }
    },
    "duration": {
      "value": null,
      "units": ""
    },
    "target": {
      "value": ""
    },
    "range": {
      "value": null,
      "units": "",
      "maxIncrements": 1,
      "minValue": null,
      "minUnits": ""
    },
    "measureTemplate": {
      "type": "",
      "size": "",
      "overrideColor": false,
      "customColor": "",
      "overrideTexture": false,
      "customTexture": ""
    },
    "attackName": "",
    "actionType": null,
    "attackBonus": "",
    "critConfirmBonus": "",
    "damage": {
      "parts": [],
      "critParts": [],
      "nonCritParts": []
    },
    "attackParts": [],
    "formulaicAttacks": {
      "count": {
        "formula": ""
      },
      "bonus": {
        "formula": ""
      },
      "label": null
    },
    "formula": "",
    "ability": {
      "attack": null,
      "damage": null,
      "damageMult": 1,
      "critRange": 20,
      "critMult": 2
    },
    "save": {
      "dc": 0,
      "type": "",
      "description": ""
    },
    "soundEffect": "",
    "powerAttack": {
      "multiplier": "",
      "damageBonus": 2,
      "critMultiplier": 1
    },
    "size": "med"
  },
  "ownership": {
    "default": 0
  },
  "_stats": {
    "systemId": "pf1",
    "systemVersion": "0.82.2",
    "coreVersion": "10.285",
    "createdTime": 1663168893105,
    "modifiedTime": 1663169294534,
    "lastModifiedBy": "pf1spheres-db"
  }
}
