{
  "_id": "8Wj1sdjYQZqMj9p2",
  "name": "Dehydration Pulse",
  "type": "feat",
  "img": "modules/pf1spheres/assets/icons/spheres/weather.webp",
  "effects": [],
  "folder": null,
  "sort": 0,
  "flags": {
    "pf1spheres": {
      "sphere": "weather"
    }
  },
  "system": {
    "description": {
      "value": "<p><strong>Prerequisites:</strong> Weather sphere (Desert Lord (advanced)), caster level 5th.</p>\n<p>While within an area with Aridity of severity level 2 or higher, you may as a standard action (but no more often than once every 1d4 rounds) spend 2 spell points to draw in the moisture from an area in a 20-foot radius surrounding yourself. Plantlife within the area dies, beds of water are drained, and living creatures within range (other than you) take 1d6 points of damage per caster level and are staggered for 1d4 rounds. A successful Fortitude save halves the damage and negates the staggered effect. Oozes, plants, and creatures with the aquatic or water subtype take double damage from this effect.</p>\n",
      "unidentified": ""
    },
    "tags": [],
    "actions": [],
    "uses": {
      "per": null,
      "value": 0,
      "maxFormula": "",
      "autoDeductChargesCost": "1"
    },
    "attackNotes": [],
    "effectNotes": [],
    "changes": [],
    "changeFlags": {
      "loseDexToAC": false,
      "noEncumbrance": false,
      "mediumArmorFullSpeed": false,
      "heavyArmorFullSpeed": false
    },
    "contextNotes": [],
    "links": {
      "children": [],
      "charges": []
    },
    "tag": "",
    "useCustomTag": false,
    "armorProf": {
      "value": [],
      "custom": ""
    },
    "weaponProf": {
      "value": [],
      "custom": ""
    },
    "languages": {
      "value": [],
      "custom": ""
    },
    "flags": {
      "boolean": {},
      "dictionary": {}
    },
    "scriptCalls": [],
    "subType": "magicTalent",
    "associations": {
      "classes": []
    },
    "showInQuickbar": false,
    "abilityType": "none",
    "crOffset": "",
    "disabled": false,
    "classSkills": {},
    "nonlethal": false,
    "duration": {
      "value": null,
      "units": ""
    },
    "target": {
      "value": ""
    },
    "attackName": "",
    "actionType": null,
    "attackBonus": "",
    "critConfirmBonus": "",
    "damage": {
      "parts": [],
      "critParts": [],
      "nonCritParts": []
    },
    "attackParts": [],
    "formulaicAttacks": {
      "count": {
        "formula": ""
      },
      "bonus": {
        "formula": ""
      },
      "label": null
    },
    "formula": "",
    "ability": {
      "attack": null,
      "damage": null,
      "damageMult": 1,
      "critRange": 20,
      "critMult": 2
    },
    "save": {
      "dc": 0,
      "type": "",
      "description": ""
    },
    "soundEffect": "",
    "powerAttack": {
      "multiplier": "",
      "damageBonus": 2,
      "critMultiplier": 1
    }
  },
  "ownership": {
    "default": 0
  },
  "_stats": {
    "systemId": "pf1",
    "systemVersion": "0.82.5",
    "coreVersion": "10.291",
    "createdTime": 1663168890547,
    "modifiedTime": 1689539974625,
    "lastModifiedBy": "pf1spheres-db"
  }
}
