{
  "name": "Imperfect Recreation",
  "type": "feat",
  "img": "modules/pf1spheres/assets/icons/spheres/creation.webp",
  "data": {
    "description": {
      "value": "<p><strong>Prerequisites:</strong> Creation sphere (Duplicate (advanced), Exquisite Detail, Fleshcraft (advanced, material)), Enhancement sphere (Animate Object (enhance), Bestow Intelligence (enhance), Bestow Life (advanced)), caster level 15th.</p>\n<p>You may use the Duplicate talent to create a living duplicate of a creature whose body you have access to (you do not need the full body, just a portion such as a hair or bone).</p>\n<p>When you use the Duplicate talent to create a duplicate of a creature, you may create it such that the duplicate possesses all of the real creature&#8217;s Hit Dice rather than half. However, duplicates created with full Hit Dice are not faithful companions in the same manner as creatures awakened with Bestow Life. Rather, such creatures are initially indifferent to their creators and are created with a random alignment (roll on the following table to determine alignment). This roll should be done secretly, without the caster immediately knowing the alignment of their creation.</p>\n<strong>Table: Imperfect Recreation Alignment</strong><br>\n<table class=\"wiki-content-table\">\n<tr>\n<th>D20 result</th>\n<th>Alignment</th>\n</tr>\n<tr>\n<td>1</td>\n<td>Lawful good</td>\n</tr>\n<tr>\n<td>2</td>\n<td>Neutral good</td>\n</tr>\n<tr>\n<td>3</td>\n<td>Chaotic good</td>\n</tr>\n<tr>\n<td>4-5</td>\n<td>Lawful neutral</td>\n</tr>\n<tr>\n<td>6-8</td>\n<td>True neutral</td>\n</tr>\n<tr>\n<td>9-11</td>\n<td>Chaotic neutral</td>\n</tr>\n<tr>\n<td>12-14</td>\n<td>Lawful evil</td>\n</tr>\n<tr>\n<td>15-17</td>\n<td>Neutral evil</td>\n</tr>\n<tr>\n<td>18-20</td>\n<td>Chaotic evil</td>\n</tr>\n</table>\n",
      "chat": "",
      "unidentified": ""
    },
    "tags": [],
    "activation": {
      "cost": 1,
      "type": ""
    },
    "unchainedAction": {
      "activation": {
        "cost": 1,
        "type": ""
      }
    },
    "duration": {
      "value": null,
      "units": ""
    },
    "target": {
      "value": ""
    },
    "range": {
      "value": null,
      "units": "",
      "maxIncrements": 1,
      "minValue": null,
      "minUnits": ""
    },
    "uses": {
      "value": 0,
      "per": null,
      "autoDeductCharges": true,
      "autoDeductChargesCost": "1",
      "maxFormula": ""
    },
    "measureTemplate": {
      "type": "",
      "size": "",
      "overrideColor": false,
      "customColor": "",
      "overrideTexture": false,
      "customTexture": ""
    },
    "attackName": "",
    "actionType": null,
    "attackBonus": "",
    "critConfirmBonus": "",
    "damage": {
      "parts": [],
      "critParts": [],
      "nonCritParts": []
    },
    "attackParts": [],
    "formulaicAttacks": {
      "count": {
        "formula": ""
      },
      "bonus": {
        "formula": ""
      },
      "label": null
    },
    "formula": "",
    "ability": {
      "attack": null,
      "damage": null,
      "damageMult": 1,
      "critRange": 20,
      "critMult": 2
    },
    "save": {
      "dc": 0,
      "type": "",
      "description": ""
    },
    "effectNotes": [],
    "attackNotes": [],
    "soundEffect": "",
    "changes": [],
    "changeFlags": {
      "loseDexToAC": false,
      "noEncumbrance": false,
      "mediumArmorFullSpeed": false,
      "heavyArmorFullSpeed": false
    },
    "contextNotes": [],
    "links": {
      "children": [],
      "charges": []
    },
    "tag": "",
    "useCustomTag": false,
    "armorProf": {
      "value": [],
      "custom": ""
    },
    "weaponProf": {
      "value": [],
      "custom": ""
    },
    "flags": {
      "boolean": [],
      "dictionary": []
    },
    "scriptCalls": [],
    "featType": "magicTalent",
    "associations": {
      "classes": []
    },
    "showInQuickbar": false,
    "nonlethal": false,
    "abilityType": "none",
    "crOffset": "",
    "disabled": false
  },
  "effects": [],
  "folder": null,
  "sort": 0,
  "permission": {
    "default": 0
  },
  "flags": {
    "pf1spheres": {
      "sphere": "creation"
    }
  },
  "_id": "Nig9BHtdhiSTiTUA"
}
