{
  "_id": "60UGvx78vqHaAqd0",
  "name": "Memetic Link",
  "type": "feat",
  "img": "modules/pf1spheres/assets/icons/spheres/mind.webp",
  "data": {
    "description": {
      "value": "<p><strong>Prerequisites:</strong> Mind sphere (Enthrall (charm), Mass Charm [mass], Powerful Charm, Project Thoughts (charm)), caster level 10th.</p>\n<p>When you place a powerful Enthrall charm on a target, you may spend an extra spell point at the time of casting to create a memetic link between you and the target. This link allows the target, if they have access to the Mind sphere, enchantment spells, or similar mind-affecting effects, to treat both itself and you as the caster of any such mind-affecting effects that they produce. All calculations involving caster level, saving throw DCs, magic skill checks, and other similar concerns related to the actual casting still use the target&#8217;s own casting ability, but you are treated as the caster for the purposes of the results. (For example: If your target uses the Read Mind charm on another target, you would both gain the information gleaned from the secondary target&#8217;s mind.) If your target possesses Memetic Link as well, he or she may cede control of an Enthrall charm he or she casts to you as well, creating a potential chain of enthralled targets, though such a chain may only go as long as your casting ability modifier (not counting yourself).</p>\n",
      "chat": "",
      "unidentified": ""
    },
    "tags": [],
    "actions": [],
    "uses": {
      "per": null,
      "value": 0,
      "maxFormula": "",
      "autoDeductCharges": true,
      "autoDeductChargesCost": "1"
    },
    "attackNotes": [],
    "effectNotes": [],
    "changes": [],
    "changeFlags": {
      "loseDexToAC": false,
      "noEncumbrance": false,
      "mediumArmorFullSpeed": false,
      "heavyArmorFullSpeed": false
    },
    "contextNotes": [],
    "links": {
      "children": [],
      "charges": []
    },
    "tag": "",
    "useCustomTag": false,
    "armorProf": {
      "value": [],
      "custom": ""
    },
    "weaponProf": {
      "value": [],
      "custom": ""
    },
    "languages": {
      "value": [],
      "custom": ""
    },
    "flags": {
      "boolean": {},
      "dictionary": {}
    },
    "scriptCalls": [],
    "featType": "magicTalent",
    "associations": {
      "classes": []
    },
    "showInQuickbar": false,
    "nonlethal": false,
    "abilityType": "none",
    "crOffset": "",
    "disabled": false,
    "classSkills": {},
    "activation": {
      "cost": 1,
      "type": ""
    },
    "unchainedAction": {
      "activation": {
        "cost": 1,
        "type": ""
      }
    },
    "duration": {
      "value": null,
      "units": ""
    },
    "target": {
      "value": ""
    },
    "range": {
      "value": null,
      "units": "",
      "maxIncrements": 1,
      "minValue": null,
      "minUnits": ""
    },
    "measureTemplate": {
      "type": "",
      "size": "",
      "overrideColor": false,
      "customColor": "",
      "overrideTexture": false,
      "customTexture": ""
    },
    "attackName": "",
    "actionType": null,
    "attackBonus": "",
    "critConfirmBonus": "",
    "damage": {
      "parts": [],
      "critParts": [],
      "nonCritParts": []
    },
    "attackParts": [],
    "formulaicAttacks": {
      "count": {
        "formula": ""
      },
      "bonus": {
        "formula": ""
      },
      "label": null
    },
    "formula": "",
    "ability": {
      "attack": null,
      "damage": null,
      "damageMult": 1,
      "critRange": 20,
      "critMult": 2
    },
    "save": {
      "dc": 0,
      "type": "",
      "description": ""
    },
    "soundEffect": "",
    "powerAttack": {
      "multiplier": "",
      "damageBonus": 2,
      "critMultiplier": 1
    },
    "size": "med"
  },
  "effects": [],
  "folder": null,
  "sort": 0,
  "permission": {
    "default": 0
  },
  "flags": {
    "pf1spheres": {
      "sphere": "mind"
    }
  }
}
