{
  "_id": "e4pN3903MnApkOwU",
  "name": "Nature’s Empathy",
  "type": "feat",
  "img": "modules/pf1spheres/assets/icons/spheres/fallen_fey.webp",
  "effects": [],
  "folder": null,
  "sort": 0,
  "flags": {
    "pf1spheres": {
      "sphere": "fallenFey"
    }
  },
  "system": {
    "description": {
      "value": "<p>You may activate the following abilities as fey-blessings:</p>\n<p><strong>Vermin Empathy:</strong> You gain wild empathy as the druid class feature (and treating your caster levels as druid levels for this purpose), but only affecting creatures of the vermin type and bypassing the immunity to mind-affecting effects granted by the vermin type. This ability treats swarms of the vermin type as if they were one creature possessing a single mind.</p>\n<p><strong>Wild Empathy:</strong> You gain wild empathy as the druid class feature, treating your caster levels as druid levels for this purpose. This ability treats swarms of the animal type as if they were one creature possessing a single mind.</p>\n",
      "unidentified": ""
    },
    "tags": ["Fey-Blessing"],
    "actions": [],
    "uses": {
      "per": null,
      "value": 0,
      "maxFormula": "",
      "autoDeductChargesCost": "1"
    },
    "attackNotes": [],
    "effectNotes": [],
    "changes": [],
    "changeFlags": {
      "loseDexToAC": false,
      "noEncumbrance": false,
      "mediumArmorFullSpeed": false,
      "heavyArmorFullSpeed": false
    },
    "contextNotes": [],
    "links": {
      "children": [],
      "charges": []
    },
    "tag": "",
    "useCustomTag": false,
    "armorProf": {
      "value": [],
      "custom": ""
    },
    "weaponProf": {
      "value": [],
      "custom": ""
    },
    "languages": {
      "value": [],
      "custom": ""
    },
    "flags": {
      "boolean": {},
      "dictionary": {}
    },
    "scriptCalls": [],
    "subType": "magicTalent",
    "associations": {
      "classes": []
    },
    "showInQuickbar": false,
    "abilityType": "none",
    "crOffset": "",
    "disabled": false,
    "classSkills": {},
    "nonlethal": false,
    "duration": {
      "value": null,
      "units": ""
    },
    "target": {
      "value": ""
    },
    "attackName": "",
    "actionType": null,
    "attackBonus": "",
    "critConfirmBonus": "",
    "damage": {
      "parts": [],
      "critParts": [],
      "nonCritParts": []
    },
    "attackParts": [],
    "formulaicAttacks": {
      "count": {
        "formula": ""
      },
      "bonus": {
        "formula": ""
      },
      "label": null
    },
    "formula": "",
    "ability": {
      "attack": null,
      "damage": null,
      "damageMult": 1,
      "critRange": 20,
      "critMult": 2
    },
    "save": {
      "dc": 0,
      "type": "",
      "description": ""
    },
    "soundEffect": "",
    "powerAttack": {
      "multiplier": "",
      "damageBonus": 2,
      "critMultiplier": 1
    }
  },
  "ownership": {
    "default": 0
  },
  "_stats": {
    "systemId": "pf1",
    "systemVersion": "9.0",
    "coreVersion": "10.291",
    "createdTime": 1663168892757,
    "modifiedTime": 1689623923404,
    "lastModifiedBy": "pf1spheres-db000"
  }
}
