{
  "name": "Time Zone",
  "type": "feat",
  "img": "modules/pf1spheres/assets/icons/spheres/time.webp",
  "data": {
    "description": {
      "value": "<p>When activating a (time) effect that targets an area, you may adjust the affected area to one of the following shapes:</p>\n<ul>\n<li><strong>Globe:</strong> Radius of up to 10 feet + 5 feet per 2 caster levels centered on your square. This effect radiates from a central point, and cannot extend through walls. You may choose to exclude yourself from the effect.</li>\n<li><strong>Wall:</strong> You may arrange your alter time as up to three 10-foot cubes, +1 cube per caster level. You must be able to perceive all areas your alter time will inhabit. You must occupy a space in or adjacent to one of the cubes.</li>\n</ul>\n<p>If you possess the Ranged Time talent, the selected area may be anywhere with range and does not have to be centered on or adjacent to you, but the effect cannot extend beyond your Ranged Time range.</p>\n",
      "chat": "",
      "unidentified": ""
    },
    "tags": [],
    "activation": {
      "cost": 1,
      "type": ""
    },
    "unchainedAction": {
      "activation": {
        "cost": 1,
        "type": ""
      }
    },
    "duration": {
      "value": null,
      "units": ""
    },
    "target": {
      "value": ""
    },
    "range": {
      "value": null,
      "units": "",
      "maxIncrements": 1,
      "minValue": null,
      "minUnits": ""
    },
    "uses": {
      "value": 0,
      "per": null,
      "autoDeductCharges": true,
      "autoDeductChargesCost": "1",
      "maxFormula": ""
    },
    "measureTemplate": {
      "type": "",
      "size": "",
      "overrideColor": false,
      "customColor": "",
      "overrideTexture": false,
      "customTexture": ""
    },
    "attackName": "",
    "actionType": null,
    "attackBonus": "",
    "critConfirmBonus": "",
    "damage": {
      "parts": [],
      "critParts": [],
      "nonCritParts": []
    },
    "attackParts": [],
    "formulaicAttacks": {
      "count": {
        "formula": ""
      },
      "bonus": {
        "formula": ""
      },
      "label": null
    },
    "formula": "",
    "ability": {
      "attack": null,
      "damage": null,
      "damageMult": 1,
      "critRange": 20,
      "critMult": 2
    },
    "save": {
      "dc": 0,
      "type": "",
      "description": ""
    },
    "effectNotes": [],
    "attackNotes": [],
    "soundEffect": "",
    "powerAttack": {
      "multiplier": "",
      "damageBonus": 2,
      "critMultiplier": 1
    },
    "changes": [],
    "changeFlags": {
      "loseDexToAC": false,
      "noEncumbrance": false,
      "mediumArmorFullSpeed": false,
      "heavyArmorFullSpeed": false
    },
    "contextNotes": [],
    "links": {
      "children": [],
      "charges": []
    },
    "tag": "",
    "useCustomTag": false,
    "armorProf": {
      "value": [],
      "custom": ""
    },
    "weaponProf": {
      "value": [],
      "custom": ""
    },
    "flags": {
      "boolean": [],
      "dictionary": []
    },
    "scriptCalls": [],
    "featType": "magicTalent",
    "associations": {
      "classes": []
    },
    "showInQuickbar": false,
    "nonlethal": false,
    "abilityType": "none",
    "crOffset": "",
    "disabled": false
  },
  "effects": [],
  "folder": null,
  "sort": 0,
  "permission": {
    "default": 0
  },
  "flags": {
    "pf1spheres": {
      "sphere": "time"
    }
  },
  "_id": "9YJN67JFXqExOsmC"
}
