{
  "_id": "322Za3weshnRJTQl",
  "name": "Fearsome Spell",
  "type": "feat",
  "img": "icons/svg/item-bag.svg",
  "effects": [],
  "folder": null,
  "sort": 0,
  "flags": {},
  "system": {
    "description": {
      "value": "<p><strong>Benefit:</strong> When a creature takes hit point damage from a fearsome talent, if that creature fails its save against the talent, it becomes shaken for a number of rounds equal to 1/2 the talent&#8217;s caster level (minimum 1 round). If the talent does not allow a save, creatures harmed by it can attempt a Will save (against the same DC the talent would have if it did allow a save) to negate the shaken effect. If the talent already causes creatures to become shaken, on a failed save, add the duration of this metamagic effect to the duration of the shaken condition imposed by the talent. A fearsome talent cannot cause a creature to become frightened, even if that creature is already shaken.</p>\n<p><strong>Cost:</strong> +2 spell points</p>\n",
      "unidentified": ""
    },
    "tags": ["Metamagic"],
    "actions": [],
    "uses": {
      "per": null,
      "value": 0,
      "maxFormula": "",
      "autoDeductChargesCost": "1"
    },
    "attackNotes": [],
    "effectNotes": [],
    "changes": [],
    "changeFlags": {
      "loseDexToAC": false,
      "noEncumbrance": false,
      "mediumArmorFullSpeed": false,
      "heavyArmorFullSpeed": false
    },
    "contextNotes": [],
    "links": {
      "children": [],
      "charges": []
    },
    "tag": "",
    "useCustomTag": false,
    "armorProf": {
      "value": [],
      "custom": ""
    },
    "weaponProf": {
      "value": [],
      "custom": ""
    },
    "languages": {
      "value": [],
      "custom": ""
    },
    "flags": {
      "boolean": {},
      "dictionary": {}
    },
    "scriptCalls": [],
    "subType": "feat",
    "associations": {
      "classes": []
    },
    "showInQuickbar": false,
    "abilityType": "none",
    "crOffset": "",
    "disabled": false,
    "classSkills": {},
    "nonlethal": false,
    "duration": {
      "value": null,
      "units": ""
    },
    "target": {
      "value": ""
    },
    "attackName": "",
    "actionType": null,
    "attackBonus": "",
    "critConfirmBonus": "",
    "damage": {
      "parts": [],
      "critParts": [],
      "nonCritParts": []
    },
    "attackParts": [],
    "formulaicAttacks": {
      "count": {
        "formula": ""
      },
      "bonus": {
        "formula": ""
      },
      "label": null
    },
    "formula": "",
    "ability": {
      "attack": null,
      "damage": null,
      "damageMult": 1,
      "critRange": 20,
      "critMult": 2
    },
    "save": {
      "dc": 0,
      "type": "",
      "description": ""
    },
    "soundEffect": ""
  },
  "ownership": {
    "default": 0
  },
  "_stats": {
    "systemId": "pf1",
    "systemVersion": "9.0",
    "coreVersion": "10.291",
    "createdTime": 1663168897504,
    "modifiedTime": 1689623924949,
    "lastModifiedBy": "pf1spheres-db000"
  }
}
