{
  "name": "Poisonous Ink",
  "type": "feat",
  "img": "icons/svg/item-bag.svg",
  "data": {
    "description": {
      "value": "<p>The ink you produce in quantity can do more than blind opponents, sometimes sickening or even killing foes.</p>\n<p><strong>Prerequisites:</strong> Cecaelia subtype, Improved Ink Jet.</p>\n<p><strong>Benefit:</strong> In addition to causing blindness for 1 minute, your ink jet becomes poisonous.</p>\n<p><strong>Ink jet</strong>&#8212;contact; <strong>save</strong> Fort DC 10 + 1/2 cecaelia&#8217;s hit dice + cecaelia&#8217;s Constitution modifier; <strong>frequency</strong> 1/round for 6 rounds; <strong>effect</strong> 1d2 Con, <strong>cure</strong> 2 saves.</p>\n",
      "chat": "",
      "unidentified": ""
    },
    "tags": [["Racial"]],
    "activation": {
      "cost": 1,
      "type": ""
    },
    "unchainedAction": {
      "activation": {
        "cost": 1,
        "type": ""
      }
    },
    "duration": {
      "value": null,
      "units": ""
    },
    "target": {
      "value": ""
    },
    "range": {
      "value": null,
      "units": "",
      "maxIncrements": 1,
      "minValue": null,
      "minUnits": ""
    },
    "uses": {
      "value": 0,
      "per": null,
      "autoDeductCharges": true,
      "autoDeductChargesCost": "1",
      "maxFormula": ""
    },
    "measureTemplate": {
      "type": "",
      "size": "",
      "overrideColor": false,
      "customColor": "",
      "overrideTexture": false,
      "customTexture": ""
    },
    "attackName": "",
    "actionType": null,
    "attackBonus": "",
    "critConfirmBonus": "",
    "damage": {
      "parts": [],
      "critParts": [],
      "nonCritParts": []
    },
    "attackParts": [],
    "formulaicAttacks": {
      "count": {
        "formula": ""
      },
      "bonus": {
        "formula": ""
      },
      "label": null
    },
    "formula": "",
    "ability": {
      "attack": null,
      "damage": null,
      "damageMult": 1,
      "critRange": 20,
      "critMult": 2
    },
    "save": {
      "dc": 0,
      "type": "",
      "description": ""
    },
    "effectNotes": [],
    "attackNotes": [],
    "soundEffect": "",
    "changes": [],
    "changeFlags": {
      "loseDexToAC": false,
      "noEncumbrance": false,
      "mediumArmorFullSpeed": false,
      "heavyArmorFullSpeed": false
    },
    "contextNotes": [],
    "links": {
      "children": [],
      "charges": []
    },
    "tag": "",
    "useCustomTag": false,
    "armorProf": {
      "value": [],
      "custom": ""
    },
    "weaponProf": {
      "value": [],
      "custom": ""
    },
    "flags": {
      "boolean": [],
      "dictionary": []
    },
    "scriptCalls": [],
    "featType": "feat",
    "associations": {
      "classes": []
    },
    "showInQuickbar": false,
    "nonlethal": false,
    "abilityType": "none",
    "crOffset": "",
    "disabled": false
  },
  "effects": [],
  "folder": null,
  "sort": 0,
  "permission": {
    "default": 0
  },
  "flags": {},
  "_id": "xwQ2HGD1Gs7CNKd3"
}
