{
  "_id": "XYK7gsb4an3SX3ZE",
  "name": "Weird Defense",
  "type": "feat",
  "img": "icons/svg/item-bag.svg",
  "effects": [],
  "folder": null,
  "sort": 0,
  "flags": {},
  "system": {
    "description": {
      "value": "<p><strong>Prerequisites:</strong> Illusion sphere (Blur (glamer), Decoy (glamer)).</p>\n<p><strong>Benefit:</strong> As a swift action, you may grant yourself a miss chance equal to 10% + 5% per 2 caster levels (maximum 95%) until the start of your next turn or until an attack misses due to this feat. Effects that ignore concealment only reduce this miss chance by half (rounded down). This is a spell-like ability. For abilities that allow for re-rolls for attacks that miss due to concealment such as the Blind-Fight feat, instead calculate the miss chance as 10% + 5% per 3 caster levels and reroll on a miss as per normal for the ability.</p>\n",
      "chat": "",
      "unidentified": ""
    },
    "tags": [["Combat"]],
    "actions": [],
    "uses": {
      "per": null,
      "value": 0,
      "maxFormula": "",
      "autoDeductCharges": true,
      "autoDeductChargesCost": "1"
    },
    "attackNotes": [],
    "effectNotes": [],
    "changes": [],
    "changeFlags": {
      "loseDexToAC": false,
      "noEncumbrance": false,
      "mediumArmorFullSpeed": false,
      "heavyArmorFullSpeed": false
    },
    "contextNotes": [],
    "links": {
      "children": [],
      "charges": []
    },
    "tag": "",
    "useCustomTag": false,
    "armorProf": {
      "value": [],
      "custom": ""
    },
    "weaponProf": {
      "value": [],
      "custom": ""
    },
    "languages": {
      "value": [],
      "custom": ""
    },
    "flags": {
      "boolean": {},
      "dictionary": {}
    },
    "scriptCalls": [],
    "featType": "feat",
    "associations": {
      "classes": []
    },
    "showInQuickbar": false,
    "abilityType": "none",
    "crOffset": "",
    "disabled": false,
    "classSkills": {},
    "nonlethal": false,
    "activation": {
      "cost": 1,
      "type": ""
    },
    "unchainedAction": {
      "activation": {
        "cost": 1,
        "type": ""
      }
    },
    "duration": {
      "value": null,
      "units": ""
    },
    "target": {
      "value": ""
    },
    "range": {
      "value": null,
      "units": "",
      "maxIncrements": 1,
      "minValue": null,
      "minUnits": ""
    },
    "measureTemplate": {
      "type": "",
      "size": "",
      "overrideColor": false,
      "customColor": "",
      "overrideTexture": false,
      "customTexture": ""
    },
    "attackName": "",
    "actionType": null,
    "attackBonus": "",
    "critConfirmBonus": "",
    "damage": {
      "parts": [],
      "critParts": [],
      "nonCritParts": []
    },
    "attackParts": [],
    "formulaicAttacks": {
      "count": {
        "formula": ""
      },
      "bonus": {
        "formula": ""
      },
      "label": null
    },
    "formula": "",
    "ability": {
      "attack": null,
      "damage": null,
      "damageMult": 1,
      "critRange": 20,
      "critMult": 2
    },
    "save": {
      "dc": 0,
      "type": "",
      "description": ""
    },
    "soundEffect": "",
    "size": "med"
  },
  "ownership": {
    "default": 0
  },
  "_stats": {
    "systemId": "pf1",
    "systemVersion": "0.82.2",
    "coreVersion": "10.285",
    "createdTime": 1663168897914,
    "modifiedTime": 1663169295718,
    "lastModifiedBy": "pf1spheres-db"
  }
}
